{"cameraMode":{"drawMode":0,"name":"Shaded","section":"Shading Mode"},"sceneLighting":false,"audioPlay":false,"sceneViewState":{"m_AlwaysRefresh":false,"showFog":true,"showSkybox":false,"showFlares":true,"showImageEffects":true,"showParticleSystems":true,"showVisualEffectGraphs":true,"m_FxEnabled":true},"in2DMode":false,"pivot":{"x":10.496969223022461,"y":4.612560749053955,"z":2.8101694583892824},"rotation":{"x":-0.010828659869730473,"y":0.7068129777908325,"z":-0.010821483097970486,"w":-0.7072389125823975},"size":1.2247449159622193,"orthographic":false}